Metadata-Version: 1.0
Name: jason
Version: 0.1.2
Summary: Lightweight helpers for views returning json data in Django.
Home-page: https://github.com/runekaagaard/jason
Author: Rune Kaagaard
Author-email: rumi.kg@gmail.com
License: GPLv2
Platform: UNKNOWN
